pyautd3_link_ethercrab/__init__.py
pyautd3_link_ethercrab/ethercrab.py
pyautd3_link_ethercrab/py.typed
pyautd3_link_ethercrab/bin/libautd3_capi_link_ethercrab.dylib
pyautd3_link_ethercrab/native_methods/__init__.py
pyautd3_link_ethercrab/native_methods/autd3_capi_link_ethercrab.py
pyautd3_link_ethercrab/native_methods/autd3_link_ethercrab.py
pyautd3_link_ethercrab-38.0.0.dist-info/licenses/LICENSE
pyautd3_link_ethercrab-38.0.0.dist-info/licenses/ThirdPartyNotices.txt
pyautd3_link_ethercrab-38.0.0.dist-info/METADATA
pyautd3_link_ethercrab-38.0.0.dist-info/WHEEL
pyautd3_link_ethercrab-38.0.0.dist-info/top_level.txt
pyautd3_link_ethercrab-38.0.0.dist-info/RECORD
