Metadata-Version: 2.4
Name: pyautd3_link_ethercrab
Version: 38.0.0
Summary: autd3-link-ethercrab library wrapper for python
Author-email: Shun Suzuki <suzuki@hapis.k.u-tokyo.ac.jp>
License-Expression: MIT
Project-URL: Repository, https://github.com/shinolab/pyautd3_link_ethercrab.git
Classifier: Programming Language :: Python :: 3.12
Classifier: Programming Language :: Python :: 3.13
Classifier: Programming Language :: Python :: 3.14
Classifier: Operating System :: Microsoft :: Windows
Classifier: Operating System :: MacOS :: MacOS X
Classifier: Operating System :: POSIX
Requires-Python: >=3.12
License-File: LICENSE
License-File: ThirdPartyNotices.txt
Requires-Dist: numpy>=2
Requires-Dist: pyautd3==38.0.0
Dynamic: license-file
